datalib/__init__.py
datalib/datasets.py
datalib/downloaded_datasets.py
datalib/keras_datasets.py
datalib/processors.py
datalib/sklearn_datasets.py
datalib/splitters.py
datalib/watermarkers/__init__.py
datalib/watermarkers/detection.py
datalib/watermarkers/watermarkers.py
datalib_dev-0.0.2.dist-info/LICENSE
datalib_dev-0.0.2.dist-info/METADATA
datalib_dev-0.0.2.dist-info/WHEEL
datalib_dev-0.0.2.dist-info/top_level.txt
datalib_dev-0.0.2.dist-info/RECORD
