Metadata-Version: 2.1
Name: datalib-dev
Version: 0.0.2
Summary: library for loading, processing, and splitting common datasets
Home-page: UNKNOWN
Author: Klas Leino
License: UNKNOWN
Platform: UNKNOWN
Requires-Python: >=3.6
Requires-Dist: cachable
Requires-Dist: numpy
Requires-Dist: scikit-learn
Requires-Dist: scikit-image
